{
  "2": "https://ia601403.us.archive.org/20/items/surat-albaqra-mp-3/surat%20albaqra%20%28mp3%29.mp3",
  "4": "https://ia600800.us.archive.org/4/items/4_20260521_20260521/4.mp3",
  "6": "https://ia601500.us.archive.org/7/items/6_20260525_20260525/6.mp3",
  "7": "https://ia600108.us.archive.org/35/items/7_20260528/7.mp3",
  "8": "https://ia902805.us.archive.org/0/items/8_20260529_20260529_1909/8.mp3",
  "9": "https://ia902906.us.archive.org/21/items/8_20260531_202605/8.mp3",
  "10": "https://ia600805.us.archive.org/25/items/yunus_202606/yunus.mp3",
  "11": "https://ia902805.us.archive.org/18/items/9_20260603_20260603/9.mp3",
  "12": "https://ia600109.us.archive.org/21/items/10_20260604_202606/10.mp3",
  "13": "https://ia601908.us.archive.org/23/items/11_20260605_20260605/11.mp3",
  "14": "https://ia600601.us.archive.org/26/items/12_20260605_20260605/12.mp3",
  "15": "https://ia600500.us.archive.org/20/items/13_20260606_20260606/13.mp3",
  "16": "https://ia600608.us.archive.org/29/items/14_20260607_202606/14.mp3",
  "17": "https://ia903109.us.archive.org/22/items/15_20260608_20260608/15.mp3",
  "18": "https://ia600104.us.archive.org/22/items/16_20260609_202606/16.mp3",
  "19": "https://ia902805.us.archive.org/25/items/17_20260610_202606/17.mp3",
  "20": "https://ia600108.us.archive.org/6/items/18_20260611_20260611/18.mp3",
  "21": "https://ia600609.us.archive.org/3/items/19_20260612_202606/19.mp3",
  "22": "https://ia600409.us.archive.org/14/items/20_20260613/20.mp3",
  "23": "https://ia600404.us.archive.org/9/items/21_20260614/21.mp3",
  "24": "https://ia601601.us.archive.org/28/items/23_20260615/23.mp3",
  "25": "https://ia600404.us.archive.org/30/items/24_20260616/24.mp3",
  "26": "https://ia600502.us.archive.org/17/items/25_20260617/25.mp3",
  "27": "https://ia601801.us.archive.org/25/items/26_20260618_202606/26.mp3",
  "28": "https://media.altilawat.com/surah%20al-qasas.mp3",
  "29": "https://ia903202.us.archive.org/13/items/28_20260620/28.mp3",
  "30": "https://ia600106.us.archive.org/15/items/29_20260620/29.mp3",
  "31": "https://ia600106.us.archive.org/0/items/31_20260621_202606/31.mp3",
  "32": "https://ia902807.us.archive.org/1/items/30_20260621/30.mp3",
  "33": "https://ia801904.us.archive.org/11/items/32_20260622/32.mp3",
  "50": "https://ia903206.us.archive.org/34/items/5_20260523_20260523/5.mp3"
}